jfr_1/__init__.py
jfr_1/module.py
jfr_1/storage.py
jfr_1-0.2.1.dist-info/licenses/LICENSE
jfr_1-0.2.1.dist-info/METADATA
jfr_1-0.2.1.dist-info/WHEEL
jfr_1-0.2.1.dist-info/top_level.txt
jfr_1-0.2.1.dist-info/RECORD
