Metadata-Version: 2.4
Name: jfr_1
Version: 0.2.1
Summary: A simple test library
Home-page: https://github.com/AnassJaafari/jfr_1
Author: Jaafari Anass
Author-email: anassjaafari.aj@gmail.com
Classifier: Programming Language :: Python :: 3
Classifier: License :: OSI Approved :: MIT License
Classifier: Operating System :: OS Independent
Requires-Python: >=3.6
License-File: LICENSE
Dynamic: author
Dynamic: author-email
Dynamic: classifier
Dynamic: description
Dynamic: description-content-type
Dynamic: home-page
Dynamic: license-file
Dynamic: requires-python
Dynamic: summary
